<?xml version="1.0" encoding="UTF-8"?>
<con:resource name="/playlists/{playlist_id}/images" path="/playlists/{playlist_id}/images" id="efa15368-78a9-4592-95de-8499c3e7e2e3" xmlns:con="http://eviware.com/soapui/config">
  <con:settings>
    <con:setting id="efa15368-78a9-4592-95de-8499c3e7e2e3fileName">%2Fplaylists%2F%7Bplaylist_id%7D%2Fimages</con:setting>
  </con:settings>
  <con:parameters/>
  <con:method name="get-playlist-cover" id="82045bfe-7f45-434d-956e-f318934c71e4" method="GET">
    <con:description>Get the current image associated with a specific playlist.</con:description>
    <con:settings/>
    <con:parameters>
      <con:parameter required="true">
        <con:name>playlist_id</con:name>
        <con:style>TEMPLATE</con:style>
      </con:parameter>
    </con:parameters>
    <con:representation type="RESPONSE">
      <con:mediaType>application/json</con:mediaType>
      <con:status>200</con:status>
      <con:params/>
      <con:description>A set of images</con:description>
      <con:sampleContent>[ {
  "url" : "https://i.scdn.co/image/ab67616d00001e02ff9ca10b55ce82ae553c8228\n",
  "height" : 300,
  "width" : 300
} ]</con:sampleContent>
    </con:representation>
    <con:representation type="RESPONSE">
      <con:mediaType>application/json</con:mediaType>
      <con:status>401</con:status>
      <con:params/>
      <con:description>Bad or expired token. This can happen if the user revoked a token or
the access token has expired. You should re-authenticate the user.</con:description>
      <con:sampleContent>{
  "error" : {
    "status" : 0,
    "message" : "string"
  }
}</con:sampleContent>
    </con:representation>
    <con:representation type="RESPONSE">
      <con:mediaType>application/json</con:mediaType>
      <con:status>403</con:status>
      <con:params/>
      <con:description>Bad OAuth request (wrong consumer key, bad nonce, expired
timestamp...). Unfortunately, re-authenticating the user won't help here.</con:description>
      <con:sampleContent>{
  "error" : {
    "status" : 0,
    "message" : "string"
  }
}</con:sampleContent>
    </con:representation>
    <con:representation type="RESPONSE">
      <con:mediaType>application/json</con:mediaType>
      <con:status>429</con:status>
      <con:params/>
      <con:description>The app has exceeded its rate limits.</con:description>
      <con:sampleContent>{
  "error" : {
    "status" : 0,
    "message" : "string"
  }
}</con:sampleContent>
    </con:representation>
    <con:request name="Request 1" id="cf479ce3-30b3-4698-a4a0-028b0a1d5df7" mediaType="application/json">
      <con:settings/>
      <con:endpoint>https://api.spotify.com/v1</con:endpoint>
      <con:parameters/>
    </con:request>
  </con:method>
  <con:method name="upload-custom-playlist-cover" id="b6f29fa8-22ac-4753-bcb2-a2a358433184" method="PUT">
    <con:description>Replace the image used to represent a specific playlist.</con:description>
    <con:settings/>
    <con:parameters>
      <con:parameter required="true">
        <con:name>playlist_id</con:name>
        <con:style>TEMPLATE</con:style>
      </con:parameter>
    </con:parameters>
    <con:representation type="RESPONSE">
      <con:mediaType>application/json</con:mediaType>
      <con:status>401</con:status>
      <con:params/>
      <con:description>Bad or expired token. This can happen if the user revoked a token or
the access token has expired. You should re-authenticate the user.</con:description>
      <con:sampleContent>{
  "error" : {
    "status" : 0,
    "message" : "string"
  }
}</con:sampleContent>
    </con:representation>
    <con:representation type="RESPONSE">
      <con:mediaType>application/json</con:mediaType>
      <con:status>403</con:status>
      <con:params/>
      <con:description>Bad OAuth request (wrong consumer key, bad nonce, expired
timestamp...). Unfortunately, re-authenticating the user won't help here.</con:description>
      <con:sampleContent>{
  "error" : {
    "status" : 0,
    "message" : "string"
  }
}</con:sampleContent>
    </con:representation>
    <con:representation type="RESPONSE">
      <con:mediaType>application/json</con:mediaType>
      <con:status>429</con:status>
      <con:params/>
      <con:description>The app has exceeded its rate limits.</con:description>
      <con:sampleContent>{
  "error" : {
    "status" : 0,
    "message" : "string"
  }
}</con:sampleContent>
    </con:representation>
    <con:representation type="REQUEST">
      <con:mediaType>image/jpeg</con:mediaType>
      <con:params/>
    </con:representation>
    <con:request name="Request 1" id="6ea992d5-43f4-4b21-be93-f5e68dd5a92a" mediaType="image/jpeg">
      <con:settings/>
      <con:endpoint>https://api.spotify.com/v1</con:endpoint>
      <con:parameters/>
    </con:request>
  </con:method>
</con:resource>
